tues/__init__.py
tues/cli/tues.py
tues/cli/tues_provider_cl.py
tues/cli/tues_provider_file.py
tues/cli/tues_provider_fm.py
tues/cli/tues_provider_icinga2.py
tues-3.2.1.dist-info/LICENSE.txt
tues-3.2.1.dist-info/METADATA
tues-3.2.1.dist-info/WHEEL
tues-3.2.1.dist-info/entry_points.txt
tues-3.2.1.dist-info/top_level.txt
tues-3.2.1.dist-info/RECORD
