Metadata-Version: 2.1
Name: tues
Version: 3.2.1
Summary: Easy remote command execution
Author-email: Michael van Bracht <michael@wontfix.org>, Marc Schmitzer <marc@solute.de>, Roland Sommer <rol@ndsommer.de>
License: The MIT License (MIT)
Project-URL: homepage, https://github.com/wontfix-org/tues/
Project-URL: repository, https://github.com/wontfix-org/tues/
Keywords: ssh,remote,shell,sudo
Classifier: License :: OSI Approved :: MIT License
Requires-Python: >=3.9
License-File: LICENSE.txt
Requires-Dist: click
Requires-Dist: asyncssh>=2.19
Requires-Dist: async-timeout
Requires-Dist: requests>=2.4
Requires-Dist: setuptools
Requires-Dist: cryptography
Provides-Extra: test
Requires-Dist: pytest; extra == "test"
Provides-Extra: dev
Requires-Dist: build; extra == "dev"
Requires-Dist: twine; extra == "dev"
Requires-Dist: tox; extra == "dev"
Provides-Extra: icinga2
Requires-Dist: icinga2api; extra == "icinga2"
